robo_orchard_core/__init__.py
robo_orchard_core/version.py
robo_orchard_core/controllers/__init__.py
robo_orchard_core/controllers/differential_ik.py
robo_orchard_core/controllers/ik.py
robo_orchard_core/datatypes/__init__.py
robo_orchard_core/datatypes/adaptor.py
robo_orchard_core/datatypes/camera_data.py
robo_orchard_core/datatypes/dataclass.py
robo_orchard_core/datatypes/geometry.py
robo_orchard_core/datatypes/joint_state.py
robo_orchard_core/datatypes/tf_graph.py
robo_orchard_core/datatypes/timestamps.py
robo_orchard_core/datatypes/uuid.py
robo_orchard_core/devices/__init__.py
robo_orchard_core/devices/cameras/__init__.py
robo_orchard_core/devices/cameras/camera.py
robo_orchard_core/envs/__init__.py
robo_orchard_core/envs/env_base.py
robo_orchard_core/envs/manager_based_env.py
robo_orchard_core/envs/task.py
robo_orchard_core/envs/managers/__init__.py
robo_orchard_core/envs/managers/manager_base.py
robo_orchard_core/envs/managers/manager_term_base.py
robo_orchard_core/envs/managers/scene_entity_cfg.py
robo_orchard_core/envs/managers/actions/__init__.py
robo_orchard_core/envs/managers/actions/action_manager.py
robo_orchard_core/envs/managers/actions/action_term.py
robo_orchard_core/envs/managers/events/__init__.py
robo_orchard_core/envs/managers/events/event_manager.py
robo_orchard_core/envs/managers/events/event_term.py
robo_orchard_core/envs/managers/observations/__init__.py
robo_orchard_core/envs/managers/observations/observation_manager.py
robo_orchard_core/envs/managers/observations/observation_term.py
robo_orchard_core/kinematics/__init__.py
robo_orchard_core/kinematics/chain.py
robo_orchard_core/policy/__init__.py
robo_orchard_core/policy/base.py
robo_orchard_core/policy/random.py
robo_orchard_core/utils/__init__.py
robo_orchard_core/utils/cli.py
robo_orchard_core/utils/config.py
robo_orchard_core/utils/dict.py
robo_orchard_core/utils/distributed.py
robo_orchard_core/utils/experimental.py
robo_orchard_core/utils/hook.py
robo_orchard_core/utils/logging.py
robo_orchard_core-0.2.0.dist-info/licenses/LICENSE
robo_orchard_core-0.2.0.dist-info/licenses/NOTICE
robo_orchard_core-0.2.0.dist-info/METADATA
robo_orchard_core-0.2.0.dist-info/WHEEL
robo_orchard_core-0.2.0.dist-info/top_level.txt
robo_orchard_core-0.2.0.dist-info/RECORD
